celery_sqlmodel_beat/__init__.py
celery_sqlmodel_beat/clockedschedule.py
celery_sqlmodel_beat/models.py
celery_sqlmodel_beat/schedulers.py
celery_sqlmodel_beat/tzcrontab.py
celery_sqlmodel_beat/util.py
celery_sqlmodel_beat-0.1.8.dist-info/LICENSE
celery_sqlmodel_beat-0.1.8.dist-info/METADATA
celery_sqlmodel_beat-0.1.8.dist-info/WHEEL
celery_sqlmodel_beat-0.1.8.dist-info/RECORD
