Metadata-Version: 2.1
Name: celery-sqlmodel-beat
Version: 0.1.8
Summary: Celery Periodic Tasks backed by the sqlmodel
License: MIT
Author: Cray
Requires-Python: >=3.10,<4.0
Classifier: License :: OSI Approved :: MIT License
Classifier: Programming Language :: Python :: 3
Classifier: Programming Language :: Python :: 3.10
Classifier: Programming Language :: Python :: 3.11
Classifier: Programming Language :: Python :: 3.12
Requires-Dist: celery (>=5.3.6,<6.0.0)
Requires-Dist: cron-descriptor (>=1.4.3,<2.0.0)
Requires-Dist: setuptools (>=69.2.0,<70.0.0)
Requires-Dist: sqlmodel (>=0.0.16,<0.0.17)
